<atlassian-plugin key="${atlassian.plugin.key}" name="${project.name}" plugins-version="2">

	<!-- Do not reuse name attributes here. All of them are considered a module in this plugin -->

    <plugin-info>
        <description>${project.description}</description>
        <version>${project.version}</version>
        <vendor name="${project.organization.name}" url="${project.organization.url}" />
    </plugin-info>
    
    <resource type="i18n" name="i18n" location="CustomFieldTypes"/>

	<!-- Web resources like CSS and JS -->
	<web-resource key="resources" name="Jira Resources">
		<!-- Since Jira 5.0, edit screen no longer supports $webResourceManager.requireResource. We need to put resources in specific context instead. -->
	 	<context>atl.general</context> <!-- General context -->
	 	<context>atl.admin</context> <!-- Admin context, i.e. custom field configuration pages -->
	 	<context>customerportal</context> <!-- Customer portal, i.e. service management pages -->
	 	<context>servicedesk.general</context> <!-- Service Desk general -->
    	<context>servicedesk.admin</context> <!-- Sercice Desk admin -->
    	
		<!-- This will transform AJS.I18n.getText('xxx') in .js files -->
		<transformation extension="js">
        	<transformer key="jsI18n"/>
		</transformation>
    	
    	<resource type="download" name="CustomField.css" location="/css/CustomFieldTypes.css"/>
    	<resource type="download" name="CustomFieldTypes.js" location="/js/CustomFieldTypes.js"/>
    	
    	<!-- Request inclusion of jquery-ui library for select2, a dropdown with autocomplete -->
		<dependency>com.atlassian.auiplugin:ajs</dependency>
    	<dependency>com.atlassian.auiplugin:jquery-ui-other</dependency>
    	<dependency>com.atlassian.auiplugin:aui-select2</dependency>
    </web-resource>

    <!-- REST APIs -->
	<rest key="RestApi" path="/igsl" version="1.0">
		<description>Provides REST API for IGSL Custom Field Types</description>
		<!-- Package(s) to scan for REST APIs -->
		<package>com.igsl.customfieldtypes.rest</package>
	</rest>

	<!-- Static Image -->
	<customfield-type name="Static Image" i18n-name-key="StaticImage.name" key="StaticImage" class="com.igsl.customfieldtypes.staticimage.StaticImage">
		<description>Read-only static image. Configure image source with default value</description>
		<!-- Preview image
		<resource type="download" name="customfieldpreview.png" location="images/StaticImage.png"/> 
		-->
		<resource type="velocity" name="view" location="templates/StaticImage/view.vm"/>
		<resource type="velocity" name="edit" location="templates/StaticImage/edit.vm"/>
		<resource type="velocity" name="xml" location="/templates/plugins/fields/xml/xml-basictext.vm"/>
	</customfield-type>
	
	<!-- Effort Table -->
	<!-- Replaced by EffortTable2
	<customfield-type name="Effort Table" i18n-name-key="EffortTable.name" key="EffortTable" class="com.igsl.customfieldtypes.efforttable.EffortTable">
		<description>Effort table</description>
		<resource type="velocity" name="view" location="templates/EffortTable/view.vm"/>
		<resource type="velocity" name="edit" location="templates/EffortTable/edit.vm"/>
		<resource type="velocity" name="xml" location="/templates/plugins/fields/xml/xml-basictext.vm"/>
	</customfield-type>
	-->
	
	<!-- Effort Table -->
	<customfield-type name="Effort Table" i18n-name-key="EffortTable.name" key="EffortTable2" class="com.igsl.customfieldtypes.efforttable.EffortTable2">
		<description>Effort table (read-only via Jira Service Management customer portal)</description>
		<resource type="velocity" name="view" location="templates/EffortTable/view2.vm"/>
		<resource type="velocity" name="edit" location="templates/EffortTable/edit2.vm"/>
		<resource type="velocity" name="xml" location="/templates/plugins/fields/xml/xml-basictext.vm"/>
	</customfield-type>
	<webwork1 key="EffortTableConfig" name="Effort Table Configuration" class="java.lang.Object">
		<description>Task List</description>
			<actions>
				<action name="com.igsl.customfieldtypes.efforttable.EffortTableConfigurationItemAction" alias="EffortTableConfigurationItemAction"> 
				<view name="input">/templates/EffortTable/edit-config.vm</view>
			</action>
		</actions> 
	</webwork1>
	
	<!-- Product Packing Note -->
	<customfield-type name="Product/File Packing Note" i18n-name-key="ProductPackingNote.name" key="ProductPackingNote" class="com.igsl.customfieldtypes.productpackingnote.ProductPackingNote">
		<description>Product/File Packing Note</description>
		<resource type="velocity" name="view" location="templates/ProductPackingNote/view.vm"/>
		<resource type="velocity" name="edit" location="templates/ProductPackingNote/edit.vm"/>
		<resource type="velocity" name="xml" location="/templates/plugins/fields/xml/xml-basictext.vm"/>
	</customfield-type>
	
	<!-- Change Request -->
	<customfield-type name="Change Request" i18n-name-key="ChangeRequest.name" key="ChangeRequest" class="com.igsl.customfieldtypes.changerequest.ChangeRequest">
		<description>Change Request</description>
		<resource type="velocity" name="view" location="templates/ChangeRequest/view.vm"/>
		<resource type="velocity" name="edit" location="templates/ChangeRequest/edit.vm"/>
		<resource type="velocity" name="xml" location="/templates/plugins/fields/xml/xml-basictext.vm"/>
	</customfield-type>
	
	<!-- URL Field -->
	<customfield-type name="URL Field" i18n-name-key="URLField.name" key="URLField" class="com.igsl.customfieldtypes.urlfield.URLField">
		<description>Custom field for URL. Displays as hyperlink on view, edit as two inputs for URL and display text. Supports multiple values.</description>
		<resource type="velocity" name="view" location="templates/URLField/view.vm"/>
		<resource type="velocity" name="edit" location="templates/URLField/edit.vm"/>
		<resource type="velocity" name="xml" location="/templates/plugins/fields/xml/xml-basictext.vm"/>
	</customfield-type>
    <webwork1 key="URLFieldConfig" name="URL Field Configuration" class="java.lang.Object">
		<description>Allow multiple values or not</description>
			<actions>
				<action name="com.igsl.customfieldtypes.URLField.URLFieldConfigurationItemAction" alias="URLFieldConfigurationItemAction"> 
				<view name="input">/templates/URLField/edit-config.vm</view>
			</action>
		</actions> 
	</webwork1>
    
</atlassian-plugin>